{
  "generatedAt": "2026-07-24T16:22:14.761Z",
  "window": {
    "from": "2026-06-20T15:08:27Z",
    "to": "2026-07-24T16:19:47Z",
    "snapshots": 30967
  },
  "headline": {
    "bamStakeSOL": 141887392.62,
    "bamStakePct": 33.1884,
    "nodeCount": 17,
    "validatorCount": 384,
    "topNode": "ams-mainnet-bam-2-tee",
    "topNodeShare": 22.497919,
    "busiestByVals": {
      "node": "fra-mainnet-bam-1-tee",
      "region": "fra",
      "vals": 94,
      "stake": 25279380.88,
      "share": 17.816509565385484
    }
  },
  "decentralization": {
    "nodeStakeHHI": 0.137946,
    "nodeNakamoto": 3,
    "regionNakamoto": 3,
    "validatorNakamoto": 27,
    "top1ValShare": 8.594038135239213,
    "top5ValShare": 17.662973023181536,
    "top10ValShare": 26.773207126594723,
    "regionCount": 15
  },
  "stats": {
    "pct": {
      "min": 27.3315,
      "max": 34.5269,
      "avg": 33.02974783156343,
      "cur": 33.1884
    },
    "hhi": {
      "min": 0.119032,
      "max": 0.155007,
      "avg": 0.12655781657893522,
      "cur": 0.137946
    },
    "vals": {
      "min": 291,
      "max": 391,
      "avg": 376.88200342299865,
      "cur": 384
    },
    "nodes": {
      "min": 12,
      "max": 18,
      "avg": 14.945910162430975,
      "cur": 17
    }
  },
  "series": [
    {
      "ts": "2026-06-20T15:08:27Z",
      "pct": 34.4851,
      "hhi": 0.120289,
      "vals": 383,
      "nodes": 14
    },
    {
      "ts": "2026-06-20T16:56:46Z",
      "pct": 34.4839,
      "hhi": 0.12054,
      "vals": 384,
      "nodes": 14
    },
    {
      "ts": "2026-06-20T19:05:45Z",
      "pct": 34.2985,
      "hhi": 0.120894,
      "vals": 379,
      "nodes": 14
    },
    {
      "ts": "2026-06-20T21:14:46Z",
      "pct": 34.2985,
      "hhi": 0.120985,
      "vals": 379,
      "nodes": 14
    },
    {
      "ts": "2026-06-20T23:23:46Z",
      "pct": 34.2985,
      "hhi": 0.120906,
      "vals": 379,
      "nodes": 14
    },
    {
      "ts": "2026-06-21T01:32:46Z",
      "pct": 34.3271,
      "hhi": 0.120922,
      "vals": 381,
      "nodes": 14
    },
    {
      "ts": "2026-06-21T03:41:46Z",
      "pct": 34.3254,
      "hhi": 0.120921,
      "vals": 380,
      "nodes": 14
    },
    {
      "ts": "2026-06-21T05:50:46Z",
      "pct": 34.3254,
      "hhi": 0.120921,
      "vals": 380,
      "nodes": 14
    },
    {
      "ts": "2026-06-21T07:59:46Z",
      "pct": 34.2985,
      "hhi": 0.120906,
      "vals": 379,
      "nodes": 14
    },
    {
      "ts": "2026-06-21T10:08:47Z",
      "pct": 34.3344,
      "hhi": 0.120926,
      "vals": 381,
      "nodes": 14
    },
    {
      "ts": "2026-06-21T12:17:46Z",
      "pct": 34.3075,
      "hhi": 0.120911,
      "vals": 380,
      "nodes": 14
    },
    {
      "ts": "2026-06-21T14:26:46Z",
      "pct": 34.339,
      "hhi": 0.120904,
      "vals": 381,
      "nodes": 14
    },
    {
      "ts": "2026-06-21T16:35:46Z",
      "pct": 34.2985,
      "hhi": 0.120985,
      "vals": 379,
      "nodes": 14
    },
    {
      "ts": "2026-06-21T18:44:46Z",
      "pct": 34.3135,
      "hhi": 0.120993,
      "vals": 380,
      "nodes": 14
    },
    {
      "ts": "2026-06-21T20:53:47Z",
      "pct": 34.2985,
      "hhi": 0.120985,
      "vals": 380,
      "nodes": 14
    },
    {
      "ts": "2026-06-21T23:02:46Z",
      "pct": 34.3727,
      "hhi": 0.12103,
      "vals": 383,
      "nodes": 14
    },
    {
      "ts": "2026-06-22T01:11:46Z",
      "pct": 34.3075,
      "hhi": 0.12099,
      "vals": 381,
      "nodes": 14
    },
    {
      "ts": "2026-06-22T03:20:46Z",
      "pct": 34.2985,
      "hhi": 0.120985,
      "vals": 380,
      "nodes": 14
    },
    {
      "ts": "2026-06-22T05:29:46Z",
      "pct": 33.9646,
      "hhi": 0.121227,
      "vals": 380,
      "nodes": 14
    },
    {
      "ts": "2026-06-22T07:38:46Z",
      "pct": 33.8563,
      "hhi": 0.121632,
      "vals": 381,
      "nodes": 14
    },
    {
      "ts": "2026-06-23T11:28:46Z",
      "pct": 34.4839,
      "hhi": 0.121215,
      "vals": 388,
      "nodes": 14
    },
    {
      "ts": "2026-06-23T13:37:46Z",
      "pct": 34.3755,
      "hhi": 0.122196,
      "vals": 389,
      "nodes": 14
    },
    {
      "ts": "2026-06-23T15:46:46Z",
      "pct": 34.3414,
      "hhi": 0.122095,
      "vals": 387,
      "nodes": 14
    },
    {
      "ts": "2026-06-23T17:55:47Z",
      "pct": 34.3122,
      "hhi": 0.122368,
      "vals": 386,
      "nodes": 14
    },
    {
      "ts": "2026-06-23T20:04:46Z",
      "pct": 34.4074,
      "hhi": 0.122078,
      "vals": 391,
      "nodes": 14
    },
    {
      "ts": "2026-06-23T22:13:45Z",
      "pct": 34.3886,
      "hhi": 0.122173,
      "vals": 390,
      "nodes": 14
    },
    {
      "ts": "2026-06-24T00:22:45Z",
      "pct": 34.3381,
      "hhi": 0.122148,
      "vals": 387,
      "nodes": 14
    },
    {
      "ts": "2026-06-24T02:31:46Z",
      "pct": 34.3658,
      "hhi": 0.122161,
      "vals": 387,
      "nodes": 14
    },
    {
      "ts": "2026-06-24T04:40:46Z",
      "pct": 34.3381,
      "hhi": 0.122148,
      "vals": 386,
      "nodes": 14
    },
    {
      "ts": "2026-06-24T06:49:46Z",
      "pct": 34.3899,
      "hhi": 0.122221,
      "vals": 388,
      "nodes": 14
    },
    {
      "ts": "2026-06-24T08:58:45Z",
      "pct": 34.0661,
      "hhi": 0.12427,
      "vals": 382,
      "nodes": 12
    },
    {
      "ts": "2026-06-24T11:07:45Z",
      "pct": 34.1073,
      "hhi": 0.124043,
      "vals": 384,
      "nodes": 12
    },
    {
      "ts": "2026-06-24T13:16:45Z",
      "pct": 33.1296,
      "hhi": 0.124105,
      "vals": 384,
      "nodes": 12
    },
    {
      "ts": "2026-06-24T15:25:45Z",
      "pct": 33.3964,
      "hhi": 0.124569,
      "vals": 387,
      "nodes": 12
    },
    {
      "ts": "2026-06-24T17:34:45Z",
      "pct": 33.3694,
      "hhi": 0.124553,
      "vals": 386,
      "nodes": 12
    },
    {
      "ts": "2026-06-24T19:43:46Z",
      "pct": 33.3515,
      "hhi": 0.124538,
      "vals": 386,
      "nodes": 12
    },
    {
      "ts": "2026-06-24T21:52:45Z",
      "pct": 33.3744,
      "hhi": 0.124399,
      "vals": 387,
      "nodes": 12
    },
    {
      "ts": "2026-06-25T00:01:47Z",
      "pct": 33.1487,
      "hhi": 0.120619,
      "vals": 387,
      "nodes": 13
    },
    {
      "ts": "2026-06-25T02:10:45Z",
      "pct": 33.1813,
      "hhi": 0.12065,
      "vals": 389,
      "nodes": 13
    },
    {
      "ts": "2026-06-25T04:27:46Z",
      "pct": 33.1347,
      "hhi": 0.120606,
      "vals": 387,
      "nodes": 13
    },
    {
      "ts": "2026-06-25T06:36:46Z",
      "pct": 33.1217,
      "hhi": 0.122091,
      "vals": 386,
      "nodes": 13
    },
    {
      "ts": "2026-06-25T08:45:45Z",
      "pct": 33.1487,
      "hhi": 0.120619,
      "vals": 387,
      "nodes": 13
    },
    {
      "ts": "2026-06-25T10:54:46Z",
      "pct": 33.1433,
      "hhi": 0.120614,
      "vals": 388,
      "nodes": 13
    },
    {
      "ts": "2026-06-25T13:03:46Z",
      "pct": 33.1217,
      "hhi": 0.120594,
      "vals": 386,
      "nodes": 13
    },
    {
      "ts": "2026-06-25T15:12:46Z",
      "pct": 33.1419,
      "hhi": 0.120612,
      "vals": 387,
      "nodes": 13
    },
    {
      "ts": "2026-06-25T17:22:45Z",
      "pct": 33.1478,
      "hhi": 0.120574,
      "vals": 388,
      "nodes": 13
    },
    {
      "ts": "2026-06-25T19:31:45Z",
      "pct": 33.178,
      "hhi": 0.120788,
      "vals": 389,
      "nodes": 13
    },
    {
      "ts": "2026-06-25T21:40:46Z",
      "pct": 33.1217,
      "hhi": 0.120667,
      "vals": 386,
      "nodes": 13
    },
    {
      "ts": "2026-06-25T23:49:46Z",
      "pct": 33.1488,
      "hhi": 0.120653,
      "vals": 388,
      "nodes": 13
    },
    {
      "ts": "2026-06-26T01:58:44Z",
      "pct": 33.1336,
      "hhi": 0.120642,
      "vals": 386,
      "nodes": 13
    },
    {
      "ts": "2026-06-26T04:07:46Z",
      "pct": 33.1483,
      "hhi": 0.120783,
      "vals": 388,
      "nodes": 13
    },
    {
      "ts": "2026-06-26T06:16:46Z",
      "pct": 33.119,
      "hhi": 0.12076,
      "vals": 386,
      "nodes": 13
    },
    {
      "ts": "2026-06-26T08:33:45Z",
      "pct": 34.109,
      "hhi": 0.121901,
      "vals": 387,
      "nodes": 13
    },
    {
      "ts": "2026-06-26T10:42:46Z",
      "pct": 34.0943,
      "hhi": 0.12187,
      "vals": 386,
      "nodes": 13
    },
    {
      "ts": "2026-06-26T12:51:46Z",
      "pct": 34.0822,
      "hhi": 0.121862,
      "vals": 385,
      "nodes": 13
    },
    {
      "ts": "2026-06-26T14:59:45Z",
      "pct": 34.0902,
      "hhi": 0.121818,
      "vals": 385,
      "nodes": 13
    },
    {
      "ts": "2026-06-26T17:09:45Z",
      "pct": 34.095,
      "hhi": 0.121779,
      "vals": 386,
      "nodes": 13
    },
    {
      "ts": "2026-06-26T19:18:45Z",
      "pct": 34.0478,
      "hhi": 0.121957,
      "vals": 384,
      "nodes": 13
    },
    {
      "ts": "2026-06-26T21:27:46Z",
      "pct": 33.7473,
      "hhi": 0.121794,
      "vals": 383,
      "nodes": 13
    },
    {
      "ts": "2026-06-26T23:38:46Z",
      "pct": 33.7912,
      "hhi": 0.121825,
      "vals": 385,
      "nodes": 13
    },
    {
      "ts": "2026-06-27T01:48:47Z",
      "pct": 33.8096,
      "hhi": 0.121838,
      "vals": 385,
      "nodes": 13
    },
    {
      "ts": "2026-06-27T03:59:46Z",
      "pct": 33.8526,
      "hhi": 0.121872,
      "vals": 388,
      "nodes": 13
    },
    {
      "ts": "2026-06-27T06:17:46Z",
      "pct": 33.8096,
      "hhi": 0.121838,
      "vals": 385,
      "nodes": 13
    },
    {
      "ts": "2026-06-27T09:05:46Z",
      "pct": 33.7817,
      "hhi": 0.121818,
      "vals": 384,
      "nodes": 13
    },
    {
      "ts": "2026-06-27T11:16:46Z",
      "pct": 33.8191,
      "hhi": 0.121846,
      "vals": 386,
      "nodes": 13
    },
    {
      "ts": "2026-06-27T13:25:45Z",
      "pct": 33.7945,
      "hhi": 0.121827,
      "vals": 385,
      "nodes": 13
    },
    {
      "ts": "2026-06-27T15:39:46Z",
      "pct": 33.7912,
      "hhi": 0.121985,
      "vals": 385,
      "nodes": 13
    },
    {
      "ts": "2026-06-27T17:49:46Z",
      "pct": 33.7945,
      "hhi": 0.121827,
      "vals": 385,
      "nodes": 13
    },
    {
      "ts": "2026-06-27T20:03:46Z",
      "pct": 33.6432,
      "hhi": 0.121318,
      "vals": 384,
      "nodes": 13
    },
    {
      "ts": "2026-06-27T22:23:46Z",
      "pct": 33.6162,
      "hhi": 0.121284,
      "vals": 382,
      "nodes": 13
    },
    {
      "ts": "2026-06-28T00:56:46Z",
      "pct": 33.6162,
      "hhi": 0.121284,
      "vals": 382,
      "nodes": 13
    },
    {
      "ts": "2026-06-28T03:24:46Z",
      "pct": 33.6562,
      "hhi": 0.121317,
      "vals": 384,
      "nodes": 13
    },
    {
      "ts": "2026-06-28T05:47:46Z",
      "pct": 33.6283,
      "hhi": 0.121294,
      "vals": 383,
      "nodes": 13
    },
    {
      "ts": "2026-06-28T07:56:46Z",
      "pct": 33.7927,
      "hhi": 0.121251,
      "vals": 383,
      "nodes": 13
    },
    {
      "ts": "2026-06-28T10:25:46Z",
      "pct": 33.8008,
      "hhi": 0.121092,
      "vals": 383,
      "nodes": 13
    },
    {
      "ts": "2026-06-28T12:36:45Z",
      "pct": 33.7728,
      "hhi": 0.121071,
      "vals": 382,
      "nodes": 13
    },
    {
      "ts": "2026-06-28T15:12:46Z",
      "pct": 33.7728,
      "hhi": 0.121071,
      "vals": 382,
      "nodes": 13
    },
    {
      "ts": "2026-06-28T17:21:45Z",
      "pct": 33.7927,
      "hhi": 0.121324,
      "vals": 383,
      "nodes": 13
    },
    {
      "ts": "2026-06-28T20:34:46Z",
      "pct": 33.8133,
      "hhi": 0.12134,
      "vals": 384,
      "nodes": 13
    },
    {
      "ts": "2026-06-28T23:10:45Z",
      "pct": 33.8042,
      "hhi": 0.121333,
      "vals": 384,
      "nodes": 13
    },
    {
      "ts": "2026-06-29T02:09:45Z",
      "pct": 33.8035,
      "hhi": 0.123265,
      "vals": 383,
      "nodes": 13
    },
    {
      "ts": "2026-06-29T05:08:45Z",
      "pct": 33.0952,
      "hhi": 0.12188,
      "vals": 380,
      "nodes": 13
    },
    {
      "ts": "2026-06-29T07:17:46Z",
      "pct": 33.0822,
      "hhi": 0.121882,
      "vals": 379,
      "nodes": 13
    },
    {
      "ts": "2026-06-29T10:06:46Z",
      "pct": 33.1029,
      "hhi": 0.121879,
      "vals": 380,
      "nodes": 13
    },
    {
      "ts": "2026-06-29T13:28:46Z",
      "pct": 33.0952,
      "hhi": 0.121694,
      "vals": 380,
      "nodes": 13
    },
    {
      "ts": "2026-06-29T17:19:46Z",
      "pct": 33.1297,
      "hhi": 0.121606,
      "vals": 381,
      "nodes": 13
    },
    {
      "ts": "2026-06-29T20:12:46Z",
      "pct": 33.1091,
      "hhi": 0.122882,
      "vals": 380,
      "nodes": 13
    },
    {
      "ts": "2026-06-30T00:10:47Z",
      "pct": 33.1508,
      "hhi": 0.121115,
      "vals": 382,
      "nodes": 13
    },
    {
      "ts": "2026-06-30T04:28:46Z",
      "pct": 33.0519,
      "hhi": 0.121971,
      "vals": 380,
      "nodes": 13
    },
    {
      "ts": "2026-06-30T08:30:47Z",
      "pct": 32.8718,
      "hhi": 0.122242,
      "vals": 380,
      "nodes": 13
    },
    {
      "ts": "2026-06-30T12:16:45Z",
      "pct": 32.9323,
      "hhi": 0.122623,
      "vals": 378,
      "nodes": 13
    },
    {
      "ts": "2026-06-30T16:30:45Z",
      "pct": 33.086,
      "hhi": 0.121271,
      "vals": 379,
      "nodes": 14
    },
    {
      "ts": "2026-06-30T20:18:46Z",
      "pct": 33.0613,
      "hhi": 0.121315,
      "vals": 380,
      "nodes": 14
    },
    {
      "ts": "2026-06-30T23:14:46Z",
      "pct": 33.1481,
      "hhi": 0.121277,
      "vals": 383,
      "nodes": 14
    },
    {
      "ts": "2026-07-01T02:50:49Z",
      "pct": 33.222,
      "hhi": 0.120253,
      "vals": 381,
      "nodes": 14
    },
    {
      "ts": "2026-07-01T06:49:46Z",
      "pct": 33.1157,
      "hhi": 0.121156,
      "vals": 380,
      "nodes": 15
    },
    {
      "ts": "2026-07-01T08:58:45Z",
      "pct": 33.1206,
      "hhi": 0.121254,
      "vals": 381,
      "nodes": 15
    },
    {
      "ts": "2026-07-01T11:53:45Z",
      "pct": 32.9004,
      "hhi": 0.121072,
      "vals": 374,
      "nodes": 15
    },
    {
      "ts": "2026-07-01T14:03:46Z",
      "pct": 32.9955,
      "hhi": 0.121278,
      "vals": 375,
      "nodes": 15
    },
    {
      "ts": "2026-07-01T16:12:45Z",
      "pct": 32.9942,
      "hhi": 0.121442,
      "vals": 375,
      "nodes": 15
    },
    {
      "ts": "2026-07-01T18:21:46Z",
      "pct": 33.0247,
      "hhi": 0.121409,
      "vals": 377,
      "nodes": 15
    },
    {
      "ts": "2026-07-01T20:31:46Z",
      "pct": 33.0897,
      "hhi": 0.12303,
      "vals": 378,
      "nodes": 14
    },
    {
      "ts": "2026-07-01T22:47:45Z",
      "pct": 33.1391,
      "hhi": 0.122976,
      "vals": 382,
      "nodes": 14
    },
    {
      "ts": "2026-07-02T01:24:47Z",
      "pct": 33.1069,
      "hhi": 0.121545,
      "vals": 380,
      "nodes": 15
    },
    {
      "ts": "2026-07-02T04:59:46Z",
      "pct": 33.1561,
      "hhi": 0.121468,
      "vals": 382,
      "nodes": 15
    },
    {
      "ts": "2026-07-02T07:56:46Z",
      "pct": 33.0997,
      "hhi": 0.121051,
      "vals": 381,
      "nodes": 15
    },
    {
      "ts": "2026-07-02T10:47:46Z",
      "pct": 32.9209,
      "hhi": 0.121267,
      "vals": 376,
      "nodes": 15
    },
    {
      "ts": "2026-07-02T14:19:48Z",
      "pct": 32.9312,
      "hhi": 0.120788,
      "vals": 374,
      "nodes": 15
    },
    {
      "ts": "2026-07-02T18:22:46Z",
      "pct": 33.0194,
      "hhi": 0.120906,
      "vals": 377,
      "nodes": 16
    },
    {
      "ts": "2026-07-02T22:21:46Z",
      "pct": 33.0472,
      "hhi": 0.126879,
      "vals": 380,
      "nodes": 16
    },
    {
      "ts": "2026-07-03T01:43:46Z",
      "pct": 33.0426,
      "hhi": 0.130475,
      "vals": 379,
      "nodes": 16
    },
    {
      "ts": "2026-07-03T04:32:46Z",
      "pct": 33.0145,
      "hhi": 0.130482,
      "vals": 378,
      "nodes": 16
    },
    {
      "ts": "2026-07-03T08:00:46Z",
      "pct": 32.9017,
      "hhi": 0.129987,
      "vals": 378,
      "nodes": 16
    },
    {
      "ts": "2026-07-03T12:12:46Z",
      "pct": 32.8977,
      "hhi": 0.130187,
      "vals": 377,
      "nodes": 15
    },
    {
      "ts": "2026-07-03T16:32:45Z",
      "pct": 32.9824,
      "hhi": 0.129092,
      "vals": 375,
      "nodes": 16
    },
    {
      "ts": "2026-07-03T20:55:47Z",
      "pct": 33.034,
      "hhi": 0.12963,
      "vals": 379,
      "nodes": 17
    },
    {
      "ts": "2026-07-04T00:37:46Z",
      "pct": 30.0661,
      "hhi": 0.146741,
      "vals": 328,
      "nodes": 16
    },
    {
      "ts": "2026-07-04T04:32:46Z",
      "pct": 30.0395,
      "hhi": 0.145153,
      "vals": 327,
      "nodes": 16
    },
    {
      "ts": "2026-07-04T08:45:46Z",
      "pct": 29.9915,
      "hhi": 0.14528,
      "vals": 326,
      "nodes": 16
    },
    {
      "ts": "2026-07-04T13:21:46Z",
      "pct": 30.2559,
      "hhi": 0.145717,
      "vals": 328,
      "nodes": 16
    },
    {
      "ts": "2026-07-04T17:59:47Z",
      "pct": 30.227,
      "hhi": 0.144691,
      "vals": 327,
      "nodes": 16
    },
    {
      "ts": "2026-07-04T22:39:45Z",
      "pct": 30.2837,
      "hhi": 0.144903,
      "vals": 329,
      "nodes": 16
    },
    {
      "ts": "2026-07-05T03:42:48Z",
      "pct": 30.0584,
      "hhi": 0.146662,
      "vals": 324,
      "nodes": 15
    },
    {
      "ts": "2026-07-05T09:24:48Z",
      "pct": 30.0561,
      "hhi": 0.146665,
      "vals": 323,
      "nodes": 15
    },
    {
      "ts": "2026-07-05T14:17:46Z",
      "pct": 30.0487,
      "hhi": 0.146673,
      "vals": 322,
      "nodes": 15
    },
    {
      "ts": "2026-07-05T19:05:45Z",
      "pct": 30.0561,
      "hhi": 0.146665,
      "vals": 323,
      "nodes": 15
    },
    {
      "ts": "2026-07-05T23:28:47Z",
      "pct": 30.0963,
      "hhi": 0.146622,
      "vals": 325,
      "nodes": 15
    },
    {
      "ts": "2026-07-06T03:43:45Z",
      "pct": 30.0996,
      "hhi": 0.146685,
      "vals": 326,
      "nodes": 15
    },
    {
      "ts": "2026-07-06T09:13:51Z",
      "pct": 30.1088,
      "hhi": 0.146424,
      "vals": 325,
      "nodes": 15
    },
    {
      "ts": "2026-07-06T13:20:46Z",
      "pct": 30.2528,
      "hhi": 0.146372,
      "vals": 327,
      "nodes": 15
    },
    {
      "ts": "2026-07-06T17:38:54Z",
      "pct": 33.393,
      "hhi": 0.127577,
      "vals": 380,
      "nodes": 17
    },
    {
      "ts": "2026-07-06T21:50:47Z",
      "pct": 33.3741,
      "hhi": 0.127931,
      "vals": 382,
      "nodes": 18
    },
    {
      "ts": "2026-07-07T01:55:47Z",
      "pct": 33.3328,
      "hhi": 0.128885,
      "vals": 381,
      "nodes": 18
    },
    {
      "ts": "2026-07-07T05:53:59Z",
      "pct": 33.3034,
      "hhi": 0.128758,
      "vals": 380,
      "nodes": 18
    },
    {
      "ts": "2026-07-07T10:01:47Z",
      "pct": 33.3666,
      "hhi": 0.12896,
      "vals": 383,
      "nodes": 18
    },
    {
      "ts": "2026-07-07T13:51:45Z",
      "pct": 33.282,
      "hhi": 0.129755,
      "vals": 377,
      "nodes": 18
    },
    {
      "ts": "2026-07-07T16:00:46Z",
      "pct": 33.282,
      "hhi": 0.130387,
      "vals": 377,
      "nodes": 17
    },
    {
      "ts": "2026-07-07T18:12:46Z",
      "pct": 33.3131,
      "hhi": 0.129789,
      "vals": 379,
      "nodes": 17
    },
    {
      "ts": "2026-07-07T21:05:46Z",
      "pct": 33.4677,
      "hhi": 0.129612,
      "vals": 381,
      "nodes": 16
    },
    {
      "ts": "2026-07-07T23:23:46Z",
      "pct": 33.9981,
      "hhi": 0.133054,
      "vals": 379,
      "nodes": 15
    },
    {
      "ts": "2026-07-08T01:32:45Z",
      "pct": 33.4131,
      "hhi": 0.131627,
      "vals": 378,
      "nodes": 14
    },
    {
      "ts": "2026-07-08T04:05:45Z",
      "pct": 33.1122,
      "hhi": 0.132857,
      "vals": 370,
      "nodes": 14
    },
    {
      "ts": "2026-07-08T06:14:45Z",
      "pct": 33.1496,
      "hhi": 0.132635,
      "vals": 370,
      "nodes": 14
    },
    {
      "ts": "2026-07-08T09:12:46Z",
      "pct": 33.1104,
      "hhi": 0.132832,
      "vals": 370,
      "nodes": 14
    },
    {
      "ts": "2026-07-08T12:49:46Z",
      "pct": 33.4367,
      "hhi": 0.13357,
      "vals": 374,
      "nodes": 14
    },
    {
      "ts": "2026-07-08T16:42:46Z",
      "pct": 33.425,
      "hhi": 0.132173,
      "vals": 373,
      "nodes": 14
    },
    {
      "ts": "2026-07-08T21:00:46Z",
      "pct": 32.6322,
      "hhi": 0.127855,
      "vals": 373,
      "nodes": 14
    },
    {
      "ts": "2026-07-09T01:18:45Z",
      "pct": 32.5537,
      "hhi": 0.127895,
      "vals": 371,
      "nodes": 14
    },
    {
      "ts": "2026-07-09T03:41:45Z",
      "pct": 32.6442,
      "hhi": 0.128073,
      "vals": 373,
      "nodes": 14
    },
    {
      "ts": "2026-07-09T07:40:46Z",
      "pct": 32.6122,
      "hhi": 0.127306,
      "vals": 372,
      "nodes": 15
    },
    {
      "ts": "2026-07-09T11:01:45Z",
      "pct": 32.6157,
      "hhi": 0.127351,
      "vals": 372,
      "nodes": 15
    },
    {
      "ts": "2026-07-09T15:05:47Z",
      "pct": 32.5737,
      "hhi": 0.127375,
      "vals": 370,
      "nodes": 15
    },
    {
      "ts": "2026-07-09T19:24:46Z",
      "pct": 32.6738,
      "hhi": 0.127415,
      "vals": 376,
      "nodes": 15
    },
    {
      "ts": "2026-07-09T22:55:46Z",
      "pct": 32.6422,
      "hhi": 0.127241,
      "vals": 373,
      "nodes": 15
    },
    {
      "ts": "2026-07-10T01:04:45Z",
      "pct": 32.6628,
      "hhi": 0.127352,
      "vals": 374,
      "nodes": 15
    },
    {
      "ts": "2026-07-10T03:16:46Z",
      "pct": 32.7023,
      "hhi": 0.127212,
      "vals": 376,
      "nodes": 15
    },
    {
      "ts": "2026-07-10T05:47:47Z",
      "pct": 33.0211,
      "hhi": 0.128515,
      "vals": 375,
      "nodes": 15
    },
    {
      "ts": "2026-07-10T10:12:45Z",
      "pct": 32.9887,
      "hhi": 0.128345,
      "vals": 374,
      "nodes": 15
    },
    {
      "ts": "2026-07-10T15:29:30Z",
      "pct": 32.7901,
      "hhi": 0.128924,
      "vals": 370,
      "nodes": 15
    },
    {
      "ts": "2026-07-10T19:03:46Z",
      "pct": 32.7823,
      "hhi": 0.127912,
      "vals": 370,
      "nodes": 15
    },
    {
      "ts": "2026-07-10T23:21:46Z",
      "pct": 32.5878,
      "hhi": 0.125923,
      "vals": 374,
      "nodes": 16
    },
    {
      "ts": "2026-07-11T03:22:12Z",
      "pct": 32.5682,
      "hhi": 0.125936,
      "vals": 372,
      "nodes": 16
    },
    {
      "ts": "2026-07-11T05:56:45Z",
      "pct": 32.5164,
      "hhi": 0.125934,
      "vals": 371,
      "nodes": 16
    },
    {
      "ts": "2026-07-11T08:14:51Z",
      "pct": 32.5196,
      "hhi": 0.125851,
      "vals": 371,
      "nodes": 16
    },
    {
      "ts": "2026-07-11T10:25:46Z",
      "pct": 32.5557,
      "hhi": 0.125931,
      "vals": 372,
      "nodes": 16
    },
    {
      "ts": "2026-07-11T12:34:46Z",
      "pct": 32.6079,
      "hhi": 0.125954,
      "vals": 373,
      "nodes": 16
    },
    {
      "ts": "2026-07-11T15:14:47Z",
      "pct": 32.46,
      "hhi": 0.125869,
      "vals": 368,
      "nodes": 16
    },
    {
      "ts": "2026-07-11T19:32:46Z",
      "pct": 32.522,
      "hhi": 0.125942,
      "vals": 372,
      "nodes": 16
    },
    {
      "ts": "2026-07-11T23:20:46Z",
      "pct": 32.5392,
      "hhi": 0.125927,
      "vals": 372,
      "nodes": 16
    },
    {
      "ts": "2026-07-12T01:29:46Z",
      "pct": 32.5267,
      "hhi": 0.12593,
      "vals": 371,
      "nodes": 16
    },
    {
      "ts": "2026-07-12T03:38:46Z",
      "pct": 32.4988,
      "hhi": 0.125867,
      "vals": 370,
      "nodes": 16
    },
    {
      "ts": "2026-07-12T05:47:46Z",
      "pct": 32.1815,
      "hhi": 0.124494,
      "vals": 370,
      "nodes": 16
    },
    {
      "ts": "2026-07-12T08:00:46Z",
      "pct": 32.1533,
      "hhi": 0.124498,
      "vals": 369,
      "nodes": 16
    },
    {
      "ts": "2026-07-12T11:26:46Z",
      "pct": 32.1291,
      "hhi": 0.124382,
      "vals": 368,
      "nodes": 16
    },
    {
      "ts": "2026-07-12T15:40:46Z",
      "pct": 32.0406,
      "hhi": 0.124335,
      "vals": 370,
      "nodes": 16
    },
    {
      "ts": "2026-07-12T19:58:46Z",
      "pct": 32.0974,
      "hhi": 0.124331,
      "vals": 373,
      "nodes": 16
    },
    {
      "ts": "2026-07-13T00:18:47Z",
      "pct": 32.0675,
      "hhi": 0.124324,
      "vals": 371,
      "nodes": 16
    },
    {
      "ts": "2026-07-13T04:36:46Z",
      "pct": 32.1108,
      "hhi": 0.124364,
      "vals": 372,
      "nodes": 16
    },
    {
      "ts": "2026-07-13T08:22:45Z",
      "pct": 32.1154,
      "hhi": 0.124308,
      "vals": 373,
      "nodes": 16
    },
    {
      "ts": "2026-07-13T11:55:46Z",
      "pct": 32.1789,
      "hhi": 0.124275,
      "vals": 377,
      "nodes": 16
    },
    {
      "ts": "2026-07-13T16:13:46Z",
      "pct": 32.0708,
      "hhi": 0.12428,
      "vals": 371,
      "nodes": 16
    },
    {
      "ts": "2026-07-13T20:31:45Z",
      "pct": 32.2261,
      "hhi": 0.122951,
      "vals": 378,
      "nodes": 17
    },
    {
      "ts": "2026-07-14T00:39:45Z",
      "pct": 32.2692,
      "hhi": 0.122957,
      "vals": 380,
      "nodes": 17
    },
    {
      "ts": "2026-07-14T03:39:46Z",
      "pct": 32.2261,
      "hhi": 0.122951,
      "vals": 378,
      "nodes": 17
    },
    {
      "ts": "2026-07-14T07:19:47Z",
      "pct": 32.1657,
      "hhi": 0.123188,
      "vals": 378,
      "nodes": 17
    },
    {
      "ts": "2026-07-14T11:38:46Z",
      "pct": 32.0972,
      "hhi": 0.123101,
      "vals": 374,
      "nodes": 17
    },
    {
      "ts": "2026-07-14T15:46:46Z",
      "pct": 33.0811,
      "hhi": 0.12611,
      "vals": 374,
      "nodes": 17
    },
    {
      "ts": "2026-07-14T20:04:47Z",
      "pct": 32.4588,
      "hhi": 0.122947,
      "vals": 381,
      "nodes": 16
    },
    {
      "ts": "2026-07-15T01:31:46Z",
      "pct": 32.2017,
      "hhi": 0.123316,
      "vals": 374,
      "nodes": 16
    },
    {
      "ts": "2026-07-15T05:31:47Z",
      "pct": 32.2261,
      "hhi": 0.123316,
      "vals": 375,
      "nodes": 16
    },
    {
      "ts": "2026-07-15T09:50:46Z",
      "pct": 32.4832,
      "hhi": 0.122028,
      "vals": 382,
      "nodes": 17
    },
    {
      "ts": "2026-07-15T13:52:47Z",
      "pct": 32.4992,
      "hhi": 0.121698,
      "vals": 382,
      "nodes": 17
    },
    {
      "ts": "2026-07-15T18:11:46Z",
      "pct": 32.4922,
      "hhi": 0.121923,
      "vals": 382,
      "nodes": 17
    },
    {
      "ts": "2026-07-15T22:36:47Z",
      "pct": 32.5119,
      "hhi": 0.127896,
      "vals": 382,
      "nodes": 17
    },
    {
      "ts": "2026-07-16T02:55:46Z",
      "pct": 32.1404,
      "hhi": 0.129554,
      "vals": 382,
      "nodes": 17
    },
    {
      "ts": "2026-07-16T07:13:47Z",
      "pct": 31.9102,
      "hhi": 0.129526,
      "vals": 383,
      "nodes": 17
    },
    {
      "ts": "2026-07-16T11:32:46Z",
      "pct": 31.8883,
      "hhi": 0.129675,
      "vals": 382,
      "nodes": 17
    },
    {
      "ts": "2026-07-16T16:05:46Z",
      "pct": 32.4438,
      "hhi": 0.129702,
      "vals": 381,
      "nodes": 17
    },
    {
      "ts": "2026-07-16T22:03:46Z",
      "pct": 32.4666,
      "hhi": 0.128395,
      "vals": 381,
      "nodes": 17
    },
    {
      "ts": "2026-07-17T00:13:44Z",
      "pct": 32.4914,
      "hhi": 0.128659,
      "vals": 382,
      "nodes": 17
    },
    {
      "ts": "2026-07-17T03:12:46Z",
      "pct": 33.0058,
      "hhi": 0.127729,
      "vals": 383,
      "nodes": 17
    },
    {
      "ts": "2026-07-17T06:35:46Z",
      "pct": 32.9623,
      "hhi": 0.127363,
      "vals": 381,
      "nodes": 17
    },
    {
      "ts": "2026-07-17T09:27:46Z",
      "pct": 32.9849,
      "hhi": 0.127454,
      "vals": 382,
      "nodes": 17
    },
    {
      "ts": "2026-07-17T11:39:45Z",
      "pct": 32.981,
      "hhi": 0.128203,
      "vals": 382,
      "nodes": 17
    },
    {
      "ts": "2026-07-17T15:20:49Z",
      "pct": 32.9505,
      "hhi": 0.128181,
      "vals": 380,
      "nodes": 17
    },
    {
      "ts": "2026-07-17T18:59:46Z",
      "pct": 33.1069,
      "hhi": 0.12854,
      "vals": 381,
      "nodes": 17
    },
    {
      "ts": "2026-07-17T23:20:46Z",
      "pct": 33.2967,
      "hhi": 0.128781,
      "vals": 385,
      "nodes": 17
    },
    {
      "ts": "2026-07-18T02:36:45Z",
      "pct": 28.7134,
      "hhi": 0.147394,
      "vals": 332,
      "nodes": 16
    },
    {
      "ts": "2026-07-18T04:45:45Z",
      "pct": 33.3525,
      "hhi": 0.128573,
      "vals": 385,
      "nodes": 17
    },
    {
      "ts": "2026-07-18T06:54:45Z",
      "pct": 33.3773,
      "hhi": 0.128588,
      "vals": 386,
      "nodes": 17
    },
    {
      "ts": "2026-07-18T09:14:46Z",
      "pct": 33.3788,
      "hhi": 0.128697,
      "vals": 385,
      "nodes": 17
    },
    {
      "ts": "2026-07-18T12:10:47Z",
      "pct": 33.4036,
      "hhi": 0.129133,
      "vals": 386,
      "nodes": 17
    },
    {
      "ts": "2026-07-18T14:50:46Z",
      "pct": 33.3997,
      "hhi": 0.128631,
      "vals": 386,
      "nodes": 17
    },
    {
      "ts": "2026-07-18T16:59:45Z",
      "pct": 33.3788,
      "hhi": 0.128635,
      "vals": 385,
      "nodes": 17
    },
    {
      "ts": "2026-07-18T19:08:45Z",
      "pct": 33.376,
      "hhi": 0.128709,
      "vals": 387,
      "nodes": 17
    },
    {
      "ts": "2026-07-18T21:17:46Z",
      "pct": 33.33,
      "hhi": 0.128694,
      "vals": 384,
      "nodes": 17
    },
    {
      "ts": "2026-07-19T00:44:46Z",
      "pct": 33.3549,
      "hhi": 0.128983,
      "vals": 385,
      "nodes": 17
    },
    {
      "ts": "2026-07-19T03:14:46Z",
      "pct": 33.3038,
      "hhi": 0.128454,
      "vals": 384,
      "nodes": 17
    },
    {
      "ts": "2026-07-19T07:38:45Z",
      "pct": 33.33,
      "hhi": 0.128965,
      "vals": 384,
      "nodes": 17
    },
    {
      "ts": "2026-07-19T12:19:46Z",
      "pct": 33.3549,
      "hhi": 0.128983,
      "vals": 385,
      "nodes": 17
    },
    {
      "ts": "2026-07-19T14:35:46Z",
      "pct": 33.283,
      "hhi": 0.128811,
      "vals": 383,
      "nodes": 17
    },
    {
      "ts": "2026-07-19T19:48:47Z",
      "pct": 33.308,
      "hhi": 0.128828,
      "vals": 384,
      "nodes": 17
    },
    {
      "ts": "2026-07-20T01:17:47Z",
      "pct": 33.283,
      "hhi": 0.129063,
      "vals": 383,
      "nodes": 17
    },
    {
      "ts": "2026-07-20T07:46:47Z",
      "pct": 33.3038,
      "hhi": 0.129825,
      "vals": 384,
      "nodes": 16
    },
    {
      "ts": "2026-07-20T13:40:47Z",
      "pct": 33.3038,
      "hhi": 0.129775,
      "vals": 384,
      "nodes": 16
    },
    {
      "ts": "2026-07-20T20:18:45Z",
      "pct": 33.2166,
      "hhi": 0.131069,
      "vals": 382,
      "nodes": 16
    },
    {
      "ts": "2026-07-21T02:45:45Z",
      "pct": 33.1954,
      "hhi": 0.131732,
      "vals": 382,
      "nodes": 16
    },
    {
      "ts": "2026-07-21T09:12:46Z",
      "pct": 30.9585,
      "hhi": 0.14971,
      "vals": 341,
      "nodes": 13
    },
    {
      "ts": "2026-07-21T14:51:46Z",
      "pct": 33.0689,
      "hhi": 0.132697,
      "vals": 380,
      "nodes": 16
    },
    {
      "ts": "2026-07-21T17:19:46Z",
      "pct": 33.1407,
      "hhi": 0.132919,
      "vals": 382,
      "nodes": 16
    },
    {
      "ts": "2026-07-21T23:19:46Z",
      "pct": 33.0116,
      "hhi": 0.132709,
      "vals": 379,
      "nodes": 17
    },
    {
      "ts": "2026-07-22T05:45:46Z",
      "pct": 33.0322,
      "hhi": 0.13281,
      "vals": 380,
      "nodes": 17
    },
    {
      "ts": "2026-07-22T12:12:47Z",
      "pct": 33.1167,
      "hhi": 0.133398,
      "vals": 382,
      "nodes": 17
    },
    {
      "ts": "2026-07-22T18:39:46Z",
      "pct": 33.0791,
      "hhi": 0.132242,
      "vals": 382,
      "nodes": 17
    },
    {
      "ts": "2026-07-23T01:06:46Z",
      "pct": 33.0216,
      "hhi": 0.132501,
      "vals": 379,
      "nodes": 17
    },
    {
      "ts": "2026-07-23T07:33:46Z",
      "pct": 32.4299,
      "hhi": 0.13888,
      "vals": 382,
      "nodes": 17
    },
    {
      "ts": "2026-07-23T14:07:46Z",
      "pct": 33.1484,
      "hhi": 0.136908,
      "vals": 382,
      "nodes": 17
    },
    {
      "ts": "2026-07-23T20:34:47Z",
      "pct": 33.1787,
      "hhi": 0.138741,
      "vals": 383,
      "nodes": 16
    },
    {
      "ts": "2026-07-24T03:01:47Z",
      "pct": 33.2203,
      "hhi": 0.138337,
      "vals": 384,
      "nodes": 17
    },
    {
      "ts": "2026-07-24T09:29:46Z",
      "pct": 33.2189,
      "hhi": 0.13828,
      "vals": 385,
      "nodes": 17
    },
    {
      "ts": "2026-07-24T16:01:47Z",
      "pct": 33.1884,
      "hhi": 0.138221,
      "vals": 384,
      "nodes": 17
    },
    {
      "ts": "2026-07-24T16:19:47Z",
      "pct": 33.1884,
      "hhi": 0.137946,
      "vals": 384,
      "nodes": 17
    }
  ],
  "nodes": [
    {
      "node": "ams-mainnet-bam-2-tee",
      "region": "ams",
      "vals": 62,
      "stake": 31921710.78,
      "share": 22.497919080973112
    },
    {
      "node": "fra-mainnet-bam-1-tee",
      "region": "fra",
      "vals": 94,
      "stake": 25279380.88,
      "share": 17.816509565385484
    },
    {
      "node": "sqq-mainnet-bam-2-tee",
      "region": "sqq",
      "vals": 21,
      "stake": 18155975.82,
      "share": 12.79604585260466
    },
    {
      "node": "sin-mainnet-bam-2-tee",
      "region": "sin",
      "vals": 51,
      "stake": 17713639.73,
      "share": 12.484294341916547
    },
    {
      "node": "ewr-mainnet-bam-2-tee",
      "region": "ewr",
      "vals": 23,
      "stake": 16261594.95,
      "share": 11.46091604657603
    },
    {
      "node": "tyo-mainnet-bam-1-tee",
      "region": "tyo",
      "vals": 43,
      "stake": 11685511.57,
      "share": 8.235764540738536
    },
    {
      "node": "lax-mainnet-bam-2-tee",
      "region": "lax",
      "vals": 23,
      "stake": 5068841.87,
      "share": 3.5724399300352423
    },
    {
      "node": "pit-mainnet-bam-2-tee",
      "region": "pit",
      "vals": 17,
      "stake": 4202499.04,
      "share": 2.96185514590353
    },
    {
      "node": "lon-mainnet-bam-2-tee",
      "region": "lon",
      "vals": 17,
      "stake": 4076783.79,
      "share": 2.8732530173635915
    },
    {
      "node": "dub-mainnet-bam-2-tee",
      "region": "dub",
      "vals": 3,
      "stake": 3277428.12,
      "share": 2.3098797287413375
    },
    {
      "node": "slc-mainnet-bam-2-tee",
      "region": "slc",
      "vals": 8,
      "stake": 1135198.06,
      "share": 0.800069716525314
    },
    {
      "node": "hkg-mainnet-bam-1-tee",
      "region": "hkg",
      "vals": 11,
      "stake": 1123988.04,
      "share": 0.7921690709554624
    },
    {
      "node": "dfw-mainnet-bam-1-tee",
      "region": "dfw",
      "vals": 5,
      "stake": 1014269.63,
      "share": 0.7148412633424824
    },
    {
      "node": "tyo-mainnet-bam-dev-tee",
      "region": "tyo",
      "vals": 1,
      "stake": 557745.72,
      "share": 0.39309040053645544
    },
    {
      "node": "sea-mainnet-bam-1-tee",
      "region": "sea",
      "vals": 3,
      "stake": 240283.45,
      "share": 0.16934799177442608
    },
    {
      "node": "iad-mainnet-bam-2-tee",
      "region": "iad",
      "vals": 1,
      "stake": 107863.29,
      "share": 0.07602034824987962
    },
    {
      "node": "dub-mainnet-bam-1-tee",
      "region": "dub",
      "vals": 1,
      "stake": 64677.89,
      "share": 0.045583958377937536
    }
  ],
  "regions": [
    {
      "region": "ams",
      "vals": 62,
      "stake": 31921710.78,
      "nodes": 1,
      "share": 22.497919080973112
    },
    {
      "region": "fra",
      "vals": 94,
      "stake": 25279380.88,
      "nodes": 1,
      "share": 17.816509565385484
    },
    {
      "region": "sqq",
      "vals": 21,
      "stake": 18155975.82,
      "nodes": 1,
      "share": 12.79604585260466
    },
    {
      "region": "sin",
      "vals": 51,
      "stake": 17713639.73,
      "nodes": 1,
      "share": 12.484294341916547
    },
    {
      "region": "ewr",
      "vals": 23,
      "stake": 16261594.95,
      "nodes": 1,
      "share": 11.46091604657603
    },
    {
      "region": "tyo",
      "vals": 44,
      "stake": 12243257.290000001,
      "nodes": 2,
      "share": 8.62885494127499
    },
    {
      "region": "lax",
      "vals": 23,
      "stake": 5068841.87,
      "nodes": 1,
      "share": 3.5724399300352423
    },
    {
      "region": "pit",
      "vals": 17,
      "stake": 4202499.04,
      "nodes": 1,
      "share": 2.96185514590353
    },
    {
      "region": "lon",
      "vals": 17,
      "stake": 4076783.79,
      "nodes": 1,
      "share": 2.8732530173635915
    },
    {
      "region": "dub",
      "vals": 4,
      "stake": 3342106.0100000002,
      "nodes": 2,
      "share": 2.355463687119275
    },
    {
      "region": "slc",
      "vals": 8,
      "stake": 1135198.06,
      "nodes": 1,
      "share": 0.800069716525314
    },
    {
      "region": "hkg",
      "vals": 11,
      "stake": 1123988.04,
      "nodes": 1,
      "share": 0.7921690709554624
    },
    {
      "region": "dfw",
      "vals": 5,
      "stake": 1014269.63,
      "nodes": 1,
      "share": 0.7148412633424824
    },
    {
      "region": "sea",
      "vals": 3,
      "stake": 240283.45,
      "nodes": 1,
      "share": 0.16934799177442608
    },
    {
      "region": "iad",
      "vals": 1,
      "stake": 107863.29,
      "nodes": 1,
      "share": 0.07602034824987962
    }
  ],
  "whales": [
    {
      "pk": "DRpbCBMxVnDK7maPM5tGv6MvB3v1sRMC86PZ8okm21hy",
      "pkShort": "DRpb…21hy",
      "node": "ewr-mainnet-bam-2-tee",
      "region": "ewr",
      "stake": 12193856.63,
      "share": 8.594038135239213
    },
    {
      "pk": "5EhGYUyQNrxgUbuYF4vbL2SZDT6RMfhq3yjeyevvULeC",
      "pkShort": "5EhG…ULeC",
      "node": "tyo-mainnet-bam-1-tee",
      "region": "tyo",
      "stake": 3598006.07,
      "share": 2.5358180200616456
    },
    {
      "pk": "Fc6NNdS2j3EmrWbU6Uqt6wsKB5ef72NjaWfNxKYbULGD",
      "pkShort": "Fc6N…ULGD",
      "node": "sin-mainnet-bam-2-tee",
      "region": "sin",
      "stake": 3314672.54,
      "share": 2.3361290097922227
    },
    {
      "pk": "krakeNd6ednDPEXxHAmoBs1qKVM8kLg79PvWF2mhXV1",
      "pkShort": "krak…hXV1",
      "node": "dub-mainnet-bam-2-tee",
      "region": "dub",
      "stake": 3012115.76,
      "share": 2.1228917556327747
    },
    {
      "pk": "GBQ2GvTzmjXMu97dr7WUnLKYTNim1aoZsYS53KYXAAAA",
      "pkShort": "GBQ2…AAAA",
      "node": "ams-mainnet-bam-2-tee",
      "region": "ams",
      "stake": 2942880.88,
      "share": 2.0740961024556785
    },
    {
      "pk": "6y7V8dL673XFzm9QyC5vvh3itWkp7wztahBd2yDqsyrK",
      "pkShort": "6y7V…syrK",
      "node": "sqq-mainnet-bam-2-tee",
      "region": "sqq",
      "stake": 2916667.66,
      "share": 2.0556214377812414
    },
    {
      "pk": "GSTampk6BJRKSDkzhaMM49R7qRx98MTPYYWvKbp83XKc",
      "pkShort": "GSTa…3XKc",
      "node": "ams-mainnet-bam-2-tee",
      "region": "ams",
      "stake": 2502415.69,
      "share": 1.763663172582418
    },
    {
      "pk": "5ejbTALcBsKQ7Cj1iSuu2mY5jqbYHqh9gF5ERXLiYj1z",
      "pkShort": "5ejb…Yj1z",
      "node": "sqq-mainnet-bam-2-tee",
      "region": "sqq",
      "stake": 2502415.68,
      "share": 1.7636631655345756
    },
    {
      "pk": "BSVckjdW2f8kcXPGcrPPtV9kUDBZ8w8PjrrGVnxgEdwq",
      "pkShort": "BSVc…Edwq",
      "node": "sqq-mainnet-bam-2-tee",
      "region": "sqq",
      "stake": 2502391.14,
      "share": 1.7636458701290085
    },
    {
      "pk": "76rcGHdPvgs8G1XrzCXUTWtwgT59AFDvpB4VbTS2TBBJ",
      "pkShort": "76rc…TBBJ",
      "node": "ams-mainnet-bam-2-tee",
      "region": "ams",
      "stake": 2502383.46,
      "share": 1.763640457385946
    },
    {
      "pk": "HpcB5Qg8Y9E73dUkot5e8HkgAJbExsYeUzniY4bCuKac",
      "pkShort": "HpcB…uKac",
      "node": "sqq-mainnet-bam-2-tee",
      "region": "sqq",
      "stake": 2500000.94,
      "share": 1.7619612948076693
    },
    {
      "pk": "DUND26mEDfFeaPsVof3YvbXDRvpuQX7HMUJrLgEWzYw4",
      "pkShort": "DUND…zYw4",
      "node": "tyo-mainnet-bam-1-tee",
      "region": "tyo",
      "stake": 2499999.99,
      "share": 1.7619606252626292
    }
  ],
  "leadershipChanges": [
    {
      "ts": "2026-06-24T05:58:46Z",
      "from": "fra-mainnet-bam-1-tee",
      "to": "fra-mainnet-bam-2-tee"
    },
    {
      "ts": "2026-06-24T18:11:45Z",
      "from": "fra-mainnet-bam-2-tee",
      "to": "ams-mainnet-bam-1-tee"
    },
    {
      "ts": "2026-06-24T22:06:45Z",
      "from": "ams-mainnet-bam-1-tee",
      "to": "fra-mainnet-bam-2-tee"
    },
    {
      "ts": "2026-06-25T05:45:47Z",
      "from": "fra-mainnet-bam-2-tee",
      "to": "ams-mainnet-bam-1-tee"
    },
    {
      "ts": "2026-06-25T06:50:46Z",
      "from": "ams-mainnet-bam-1-tee",
      "to": "fra-mainnet-bam-2-tee"
    },
    {
      "ts": "2026-06-25T06:51:46Z",
      "from": "fra-mainnet-bam-2-tee",
      "to": "ams-mainnet-bam-1-tee"
    },
    {
      "ts": "2026-06-25T07:08:46Z",
      "from": "ams-mainnet-bam-1-tee",
      "to": "fra-mainnet-bam-2-tee"
    },
    {
      "ts": "2026-06-25T07:26:47Z",
      "from": "fra-mainnet-bam-2-tee",
      "to": "ams-mainnet-bam-1-tee"
    },
    {
      "ts": "2026-06-25T08:38:45Z",
      "from": "ams-mainnet-bam-1-tee",
      "to": "fra-mainnet-bam-2-tee"
    },
    {
      "ts": "2026-06-29T01:57:46Z",
      "from": "fra-mainnet-bam-2-tee",
      "to": "ams-mainnet-bam-1-tee"
    },
    {
      "ts": "2026-06-29T02:43:46Z",
      "from": "ams-mainnet-bam-1-tee",
      "to": "fra-mainnet-bam-2-tee"
    },
    {
      "ts": "2026-06-29T21:28:46Z",
      "from": "fra-mainnet-bam-2-tee",
      "to": "ams-mainnet-bam-1-tee"
    },
    {
      "ts": "2026-06-29T21:54:46Z",
      "from": "ams-mainnet-bam-1-tee",
      "to": "fra-mainnet-bam-2-tee"
    },
    {
      "ts": "2026-06-29T22:04:46Z",
      "from": "fra-mainnet-bam-2-tee",
      "to": "ams-mainnet-bam-1-tee"
    },
    {
      "ts": "2026-06-29T22:22:46Z",
      "from": "ams-mainnet-bam-1-tee",
      "to": "fra-mainnet-bam-2-tee"
    },
    {
      "ts": "2026-06-30T02:14:46Z",
      "from": "fra-mainnet-bam-2-tee",
      "to": "ams-mainnet-bam-1-tee"
    },
    {
      "ts": "2026-06-30T03:38:46Z",
      "from": "ams-mainnet-bam-1-tee",
      "to": "fra-mainnet-bam-2-tee"
    },
    {
      "ts": "2026-06-30T17:00:45Z",
      "from": "fra-mainnet-bam-2-tee",
      "to": "ams-mainnet-bam-1-tee"
    },
    {
      "ts": "2026-06-30T17:02:46Z",
      "from": "ams-mainnet-bam-1-tee",
      "to": "fra-mainnet-bam-2-tee"
    },
    {
      "ts": "2026-07-01T00:48:47Z",
      "from": "fra-mainnet-bam-2-tee",
      "to": "fra-mainnet-bam-1-tee"
    },
    {
      "ts": "2026-07-01T02:41:46Z",
      "from": "fra-mainnet-bam-1-tee",
      "to": "ams-mainnet-bam-1-tee"
    },
    {
      "ts": "2026-07-01T02:44:46Z",
      "from": "ams-mainnet-bam-1-tee",
      "to": "fra-mainnet-bam-1-tee"
    },
    {
      "ts": "2026-07-01T03:54:46Z",
      "from": "fra-mainnet-bam-1-tee",
      "to": "fra-mainnet-bam-2-tee"
    },
    {
      "ts": "2026-07-01T04:30:47Z",
      "from": "fra-mainnet-bam-2-tee",
      "to": "ams-mainnet-bam-1-tee"
    },
    {
      "ts": "2026-07-01T04:44:46Z",
      "from": "ams-mainnet-bam-1-tee",
      "to": "fra-mainnet-bam-2-tee"
    },
    {
      "ts": "2026-07-01T11:41:46Z",
      "from": "fra-mainnet-bam-2-tee",
      "to": "ams-mainnet-bam-1-tee"
    },
    {
      "ts": "2026-07-01T11:53:45Z",
      "from": "ams-mainnet-bam-1-tee",
      "to": "fra-mainnet-bam-2-tee"
    },
    {
      "ts": "2026-07-01T12:12:46Z",
      "from": "fra-mainnet-bam-2-tee",
      "to": "ams-mainnet-bam-1-tee"
    },
    {
      "ts": "2026-07-01T13:16:46Z",
      "from": "ams-mainnet-bam-1-tee",
      "to": "fra-mainnet-bam-2-tee"
    },
    {
      "ts": "2026-07-01T14:44:46Z",
      "from": "fra-mainnet-bam-2-tee",
      "to": "ams-mainnet-bam-1-tee"
    },
    {
      "ts": "2026-07-01T15:00:46Z",
      "from": "ams-mainnet-bam-1-tee",
      "to": "fra-mainnet-bam-2-tee"
    },
    {
      "ts": "2026-07-01T15:08:46Z",
      "from": "fra-mainnet-bam-2-tee",
      "to": "ams-mainnet-bam-1-tee"
    },
    {
      "ts": "2026-07-01T15:19:45Z",
      "from": "ams-mainnet-bam-1-tee",
      "to": "fra-mainnet-bam-2-tee"
    },
    {
      "ts": "2026-07-01T15:20:45Z",
      "from": "fra-mainnet-bam-2-tee",
      "to": "ams-mainnet-bam-1-tee"
    },
    {
      "ts": "2026-07-01T15:25:45Z",
      "from": "ams-mainnet-bam-1-tee",
      "to": "fra-mainnet-bam-2-tee"
    },
    {
      "ts": "2026-07-01T16:28:46Z",
      "from": "fra-mainnet-bam-2-tee",
      "to": "ams-mainnet-bam-1-tee"
    },
    {
      "ts": "2026-07-01T16:50:46Z",
      "from": "ams-mainnet-bam-1-tee",
      "to": "fra-mainnet-bam-2-tee"
    },
    {
      "ts": "2026-07-01T18:58:46Z",
      "from": "fra-mainnet-bam-2-tee",
      "to": "ams-mainnet-bam-1-tee"
    },
    {
      "ts": "2026-07-01T20:23:46Z",
      "from": "ams-mainnet-bam-1-tee",
      "to": "fra-mainnet-bam-2-tee"
    },
    {
      "ts": "2026-07-01T21:11:46Z",
      "from": "fra-mainnet-bam-2-tee",
      "to": "ams-mainnet-bam-1-tee"
    },
    {
      "ts": "2026-07-01T21:40:46Z",
      "from": "ams-mainnet-bam-1-tee",
      "to": "fra-mainnet-bam-2-tee"
    },
    {
      "ts": "2026-07-01T22:20:46Z",
      "from": "fra-mainnet-bam-2-tee",
      "to": "ams-mainnet-bam-1-tee"
    },
    {
      "ts": "2026-07-01T23:22:47Z",
      "from": "ams-mainnet-bam-1-tee",
      "to": "fra-mainnet-bam-2-tee"
    },
    {
      "ts": "2026-07-02T03:30:46Z",
      "from": "fra-mainnet-bam-2-tee",
      "to": "ams-mainnet-bam-1-tee"
    },
    {
      "ts": "2026-07-02T03:50:47Z",
      "from": "ams-mainnet-bam-1-tee",
      "to": "fra-mainnet-bam-2-tee"
    },
    {
      "ts": "2026-07-02T20:37:46Z",
      "from": "fra-mainnet-bam-2-tee",
      "to": "ams-mainnet-bam-1-tee"
    },
    {
      "ts": "2026-07-04T12:12:45Z",
      "from": "ams-mainnet-bam-1-tee",
      "to": "fra-mainnet-bam-2-tee"
    },
    {
      "ts": "2026-07-04T12:16:45Z",
      "from": "fra-mainnet-bam-2-tee",
      "to": "ams-mainnet-bam-1-tee"
    },
    {
      "ts": "2026-07-08T02:07:48Z",
      "from": "ams-mainnet-bam-1-tee",
      "to": "ams-mainnet-bam-2-tee"
    },
    {
      "ts": "2026-07-08T17:40:46Z",
      "from": "ams-mainnet-bam-2-tee",
      "to": "fra-mainnet-bam-1-tee"
    },
    {
      "ts": "2026-07-08T17:50:46Z",
      "from": "fra-mainnet-bam-1-tee",
      "to": "ams-mainnet-bam-2-tee"
    },
    {
      "ts": "2026-07-08T18:40:46Z",
      "from": "ams-mainnet-bam-2-tee",
      "to": "fra-mainnet-bam-1-tee"
    },
    {
      "ts": "2026-07-08T19:00:46Z",
      "from": "fra-mainnet-bam-1-tee",
      "to": "ams-mainnet-bam-2-tee"
    },
    {
      "ts": "2026-07-08T20:34:46Z",
      "from": "ams-mainnet-bam-2-tee",
      "to": "fra-mainnet-bam-1-tee"
    },
    {
      "ts": "2026-07-08T20:50:45Z",
      "from": "fra-mainnet-bam-1-tee",
      "to": "ams-mainnet-bam-2-tee"
    },
    {
      "ts": "2026-07-10T04:47:46Z",
      "from": "ams-mainnet-bam-2-tee",
      "to": "fra-mainnet-bam-1-tee"
    },
    {
      "ts": "2026-07-10T05:21:46Z",
      "from": "fra-mainnet-bam-1-tee",
      "to": "ams-mainnet-bam-2-tee"
    },
    {
      "ts": "2026-07-14T14:14:46Z",
      "from": "ams-mainnet-bam-2-tee",
      "to": "fra-mainnet-bam-1-tee"
    },
    {
      "ts": "2026-07-14T17:52:47Z",
      "from": "fra-mainnet-bam-1-tee",
      "to": "ams-mainnet-bam-2-tee"
    },
    {
      "ts": "2026-07-22T20:45:45Z",
      "from": "ams-mainnet-bam-2-tee",
      "to": "ams-mainnet-bam-1-tee"
    },
    {
      "ts": "2026-07-24T05:04:47Z",
      "from": "ams-mainnet-bam-1-tee",
      "to": "ams-mainnet-bam-2-tee"
    }
  ],
  "detections": {
    "validated": [
      {
        "ts": "2026-06-24T05:58:46Z",
        "from": "fra-mainnet-bam-1-tee",
        "to": "fra-mainnet-bam-2-tee",
        "region": "fra",
        "lead_min": 22,
        "precursorTs": "2026-06-24T05:36:46Z",
        "precursorNode": "fra-mainnet-bam-2-tee"
      }
    ],
    "rolloverPrecursors": 15,
    "liveCutovers": 60,
    "liveSignals": 153,
    "feed": [
      {
        "ts": "2026-07-24T05:58:46Z",
        "kind": "SIGNAL_XREGION",
        "region": "hkg",
        "detail": "new hkg-mainnet-bam-1-tee",
        "structural": null
      },
      {
        "ts": "2026-07-24T05:55:47Z",
        "kind": "SIGNAL_XREGION",
        "region": "dfw",
        "detail": "new dfw-mainnet-bam-1-tee",
        "structural": null
      },
      {
        "ts": "2026-07-24T05:52:46Z",
        "kind": "SIGNAL_XREGION",
        "region": "lax",
        "detail": "new lax-mainnet-bam-2-tee",
        "structural": null
      },
      {
        "ts": "2026-07-24T05:43:46Z",
        "kind": "SIGNAL_XREGION",
        "region": "lon",
        "detail": "new lon-mainnet-bam-2-tee",
        "structural": null
      },
      {
        "ts": "2026-07-24T05:37:46Z",
        "kind": "SIGNAL_XREGION",
        "region": "pit",
        "detail": "new pit-mainnet-bam-2-tee",
        "structural": null
      },
      {
        "ts": "2026-07-24T05:25:47Z",
        "kind": "SIGNAL_XREGION",
        "region": "fra",
        "detail": "new fra-mainnet-bam-1-tee",
        "structural": null
      },
      {
        "ts": "2026-07-24T05:19:47Z",
        "kind": "SIGNAL_XREGION",
        "region": "ewr",
        "detail": "new ewr-mainnet-bam-2-tee",
        "structural": null
      },
      {
        "ts": "2026-07-24T05:13:47Z",
        "kind": "SIGNAL_XREGION",
        "region": "sin",
        "detail": "new sin-mainnet-bam-2-tee",
        "structural": null
      },
      {
        "ts": "2026-07-24T05:04:47Z",
        "kind": "CUTOVER",
        "region": "ams",
        "detail": "ams-mainnet-bam-1-tee → ams-mainnet-bam-2-tee",
        "structural": false
      },
      {
        "ts": "2026-07-24T05:04:47Z",
        "kind": "SIGNAL",
        "region": "ams",
        "detail": "new ams-mainnet-bam-2-tee",
        "structural": null
      },
      {
        "ts": "2026-07-24T04:52:46Z",
        "kind": "SIGNAL_XREGION",
        "region": "tyo",
        "detail": "new tyo-mainnet-bam-1-tee",
        "structural": null
      },
      {
        "ts": "2026-07-24T04:49:47Z",
        "kind": "SIGNAL_XREGION",
        "region": "sqq",
        "detail": "new sqq-mainnet-bam-2-tee",
        "structural": null
      }
    ]
  }
}